st_ner_annotate/__init__.py
st_ner_annotate/frontend/README.md
st_ner_annotate/frontend/package.json
st_ner_annotate/frontend/public/bootstrap.min.css
st_ner_annotate/frontend/public/build/bundle.css
st_ner_annotate/frontend/public/build/bundle.css.map
st_ner_annotate/frontend/public/build/bundle.js
st_ner_annotate/frontend/public/build/bundle.js.map
st_ner_annotate/frontend/public/index.html
st_ner_annotate/frontend/rollup.config.js
st_ner_annotate/frontend/src/StreamlitNERAnnotate.svelte
st_ner_annotate/frontend/src/components/MarkedWord.svelte
st_ner_annotate/frontend/src/components/Word.svelte
st_ner_annotate/frontend/src/main.ts
st_ner_annotate/frontend/src/streamlit/ArrowTable.ts
st_ner_annotate/frontend/src/streamlit/WithStreamlitConnection.svelte
st_ner_annotate/frontend/src/streamlit/index.ts
st_ner_annotate/frontend/src/streamlit/setStreamlitLifecycle.ts
st_ner_annotate/frontend/src/streamlit/streamlit.ts
st_ner_annotate/frontend/tsconfig.json
st_ner_annotate-0.1.0.dist-info/LICENSE
st_ner_annotate-0.1.0.dist-info/METADATA
st_ner_annotate-0.1.0.dist-info/WHEEL
st_ner_annotate-0.1.0.dist-info/RECORD
